takopi_scripts/__init__.py
takopi_scripts/backend.py
takopi_scripts-0.1.2.dist-info/METADATA
takopi_scripts-0.1.2.dist-info/WHEEL
takopi_scripts-0.1.2.dist-info/entry_points.txt
takopi_scripts-0.1.2.dist-info/RECORD
