Metadata-Version: 2.4
Name: takopi-scripts
Version: 0.1.2
Summary: Dynamic script runner plugin for takopi
Requires-Python: >=3.14
Requires-Dist: takopi
